{"/expert":"https://gpuzelenograd.github.io/EXPERT","/experts":"https://gpuzelenograd.github.io/EXPERT","/EXPERTS":"https://gpuzelenograd.github.io/EXPERT","/nv":"https://gpuzelenograd.github.io/NV","/nV":"https://gpuzelenograd.github.io/NV","/Nv":"https://gpuzelenograd.github.io/NV","/n":"https://gpuzelenograd.github.io/NVIDIA","/N":"https://gpuzelenograd.github.io/NVIDIA","/nvidia":"https://gpuzelenograd.github.io/NVIDIA","/nVidia":"https://gpuzelenograd.github.io/NVIDIA","/Nvidia":"https://gpuzelenograd.github.io/NVIDIA","/NVidia":"https://gpuzelenograd.github.io/NVIDIA","/nvidiaRU":"https://gpuzelenograd.github.io/NVIDIARU","/nVidiaRU":"https://gpuzelenograd.github.io/NVIDIARU","/NvidiaRU":"https://gpuzelenograd.github.io/NVIDIARU","/NVidiaRU":"https://gpuzelenograd.github.io/NVIDIARU","/NVIDIAru":"https://gpuzelenograd.github.io/NVIDIARU","/nvidiaru":"https://gpuzelenograd.github.io/NVIDIARU","/nVidiaru":"https://gpuzelenograd.github.io/NVIDIARU","/Nvidiaru":"https://gpuzelenograd.github.io/NVIDIARU","/NVidiaru":"https://gpuzelenograd.github.io/NVIDIARU","/NVIDIARu":"https://gpuzelenograd.github.io/NVIDIARU","/nvidiaRu":"https://gpuzelenograd.github.io/NVIDIARU","/nVidiaRu":"https://gpuzelenograd.github.io/NVIDIARU","/NvidiaRu":"https://gpuzelenograd.github.io/NVIDIARU","/NVidiaRu":"https://gpuzelenograd.github.io/NVIDIARU","/Rx470RU":"https://gpuzelenograd.github.io/RX470RU","/rx470RU":"https://gpuzelenograd.github.io/RX470RU","/RX470Ru":"https://gpuzelenograd.github.io/RX470RU","/Rx470Ru":"https://gpuzelenograd.github.io/RX470RU","/rx470Ru":"https://gpuzelenograd.github.io/RX470RU","/RX470ru":"https://gpuzelenograd.github.io/RX470RU","/Rx470ru":"https://gpuzelenograd.github.io/RX470RU","/rx470ru":"https://gpuzelenograd.github.io/RX470RU"}